<profile>

<RTLDesignHierarchy>
<TopModule>
<ModuleName>conv2D0</ModuleName>
<InstancesList>
<Instance>
<InstName>grp_conv2D0_Pipeline_readImg_fu_168</InstName>
<ModuleName>conv2D0_Pipeline_readImg</ModuleName>
<IsCompInst>true</IsCompInst>
<ID>168</ID>
</Instance>
<Instance>
<InstName>grp_conv2D0_Pipeline_readweights_fu_180</InstName>
<ModuleName>conv2D0_Pipeline_readweights</ModuleName>
<IsCompInst>true</IsCompInst>
<ID>180</ID>
</Instance>
<Instance>
<InstName>grp_conv2D0_Pipeline_loop_orow_loop_ocol_fu_192</InstName>
<ModuleName>conv2D0_Pipeline_loop_orow_loop_ocol</ModuleName>
<IsCompInst>true</IsCompInst>
<ID>192</ID>
</Instance>
<Instance>
<InstName>grp_conv2D0_Pipeline_writeImg_fu_215</InstName>
<ModuleName>conv2D0_Pipeline_writeImg</ModuleName>
<IsCompInst>true</IsCompInst>
<ID>215</ID>
</Instance>
</InstancesList>
</TopModule>
</RTLDesignHierarchy>

<ModuleInformation>
<Module>
<Name>conv2D0_Pipeline_readImg</Name>
<Loops>
<readImg></readImg>
</Loops>
<PerformanceEstimates>
<SummaryOfTimingAnalysis>
<TargetClockPeriod>10.00</TargetClockPeriod>
<ClockUncertainty>2.70</ClockUncertainty>
<EstimatedClockPeriod>5.892</EstimatedClockPeriod>
</SummaryOfTimingAnalysis>
<SummaryOfOverallLatency>
<Best-caseLatency>18</Best-caseLatency>
<Average-caseLatency>18</Average-caseLatency>
<Worst-caseLatency>18</Worst-caseLatency>
<Best-caseRealTimeLatency>0.180 us</Best-caseRealTimeLatency>
<Average-caseRealTimeLatency>0.180 us</Average-caseRealTimeLatency>
<Worst-caseRealTimeLatency>0.180 us</Worst-caseRealTimeLatency>
<PipelineInitiationInterval>18</PipelineInitiationInterval>
<PipelineType>no</PipelineType>
</SummaryOfOverallLatency>
<SummaryOfLoopLatency>
<readImg>
<Name>readImg</Name>
<Slack>7.30</Slack>
<TripCount>16</TripCount>
<Latency>16</Latency>
<AbsoluteTimeLatency>0.160 us</AbsoluteTimeLatency>
<PipelineII>1</PipelineII>
<PipelineDepth>2</PipelineDepth>
<PipelineType>yes</PipelineType>
<InstanceList>
</InstanceList>
</readImg>
</SummaryOfLoopLatency>
<SummaryOfViolations>
<IssueType>-</IssueType>
<ViolationType>-</ViolationType>
<SourceLocation>conv2D0.cpp:21</SourceLocation>
<SummaryOfLoopViolations>
<readImg>
<Name>readImg</Name>
<IssueType>-</IssueType>
<ViolationType>-</ViolationType>
<SourceLocation>conv2D0.cpp:21</SourceLocation>
</readImg>
</SummaryOfLoopViolations>
</SummaryOfViolations>
</PerformanceEstimates>
<AreaEstimates>
<Resources>
<FF>15</FF>
<AVAIL_FF>35200</AVAIL_FF>
<UTIL_FF>~0</UTIL_FF>
<LUT>73</LUT>
<AVAIL_LUT>17600</AVAIL_LUT>
<UTIL_LUT>~0</UTIL_LUT>
<BRAM_18K>0</BRAM_18K>
<AVAIL_BRAM>120</AVAIL_BRAM>
<UTIL_BRAM>0</UTIL_BRAM>
<DSP>0</DSP>
<AVAIL_DSP>80</AVAIL_DSP>
<UTIL_DSP>0</UTIL_DSP>
<URAM>0</URAM>
<AVAIL_URAM>0</AVAIL_URAM>
<UTIL_URAM>0</UTIL_URAM>
</Resources>
</AreaEstimates>
<InterfaceSummary>
<RtlPorts>
<name>ap_clk</name>
<Object>conv2D0_Pipeline_readImg</Object>
<Type>return value</Type>
<Scope></Scope>
<IOProtocol>ap_ctrl_hs</IOProtocol>
<IOConfig></IOConfig>
<Dir>in</Dir>
<Bits>1</Bits>
<Attribute>control</Attribute>
</RtlPorts>
<RtlPorts>
<name>ap_rst</name>
<Object>conv2D0_Pipeline_readImg</Object>
<Type>return value</Type>
<Scope></Scope>
<IOProtocol>ap_ctrl_hs</IOProtocol>
<IOConfig></IOConfig>
<Dir>in</Dir>
<Bits>1</Bits>
<Attribute>control</Attribute>
</RtlPorts>
<RtlPorts>
<name>ap_start</name>
<Object>conv2D0_Pipeline_readImg</Object>
<Type>return value</Type>
<Scope></Scope>
<IOProtocol>ap_ctrl_hs</IOProtocol>
<IOConfig></IOConfig>
<Dir>in</Dir>
<Bits>1</Bits>
<Attribute>control</Attribute>
</RtlPorts>
<RtlPorts>
<name>ap_done</name>
<Object>conv2D0_Pipeline_readImg</Object>
<Type>return value</Type>
<Scope></Scope>
<IOProtocol>ap_ctrl_hs</IOProtocol>
<IOConfig></IOConfig>
<Dir>out</Dir>
<Bits>1</Bits>
<Attribute>control</Attribute>
</RtlPorts>
<RtlPorts>
<name>ap_idle</name>
<Object>conv2D0_Pipeline_readImg</Object>
<Type>return value</Type>
<Scope></Scope>
<IOProtocol>ap_ctrl_hs</IOProtocol>
<IOConfig></IOConfig>
<Dir>out</Dir>
<Bits>1</Bits>
<Attribute>control</Attribute>
</RtlPorts>
<RtlPorts>
<name>ap_ready</name>
<Object>conv2D0_Pipeline_readImg</Object>
<Type>return value</Type>
<Scope></Scope>
<IOProtocol>ap_ctrl_hs</IOProtocol>
<IOConfig></IOConfig>
<Dir>out</Dir>
<Bits>1</Bits>
<Attribute>control</Attribute>
</RtlPorts>
<RtlPorts>
<name>img_inT_1_address0</name>
<Object>img_inT_1</Object>
<Type>array</Type>
<Scope></Scope>
<IOProtocol>ap_memory</IOProtocol>
<IOConfig></IOConfig>
<Dir>out</Dir>
<Bits>3</Bits>
<Attribute>address</Attribute>
</RtlPorts>
<RtlPorts>
<name>img_inT_1_ce0</name>
<Object>img_inT_1</Object>
<Type>array</Type>
<Scope></Scope>
<IOProtocol>ap_memory</IOProtocol>
<IOConfig></IOConfig>
<Dir>out</Dir>
<Bits>1</Bits>
<Attribute>control</Attribute>
</RtlPorts>
<RtlPorts>
<name>img_inT_1_we0</name>
<Object>img_inT_1</Object>
<Type>array</Type>
<Scope></Scope>
<IOProtocol>ap_memory</IOProtocol>
<IOConfig></IOConfig>
<Dir>out</Dir>
<Bits>1</Bits>
<Attribute>control</Attribute>
</RtlPorts>
<RtlPorts>
<name>img_inT_1_d0</name>
<Object>img_inT_1</Object>
<Type>array</Type>
<Scope></Scope>
<IOProtocol>ap_memory</IOProtocol>
<IOConfig></IOConfig>
<Dir>out</Dir>
<Bits>8</Bits>
<Attribute>data</Attribute>
</RtlPorts>
<RtlPorts>
<name>img_inT_address0</name>
<Object>img_inT</Object>
<Type>array</Type>
<Scope></Scope>
<IOProtocol>ap_memory</IOProtocol>
<IOConfig></IOConfig>
<Dir>out</Dir>
<Bits>3</Bits>
<Attribute>address</Attribute>
</RtlPorts>
<RtlPorts>
<name>img_inT_ce0</name>
<Object>img_inT</Object>
<Type>array</Type>
<Scope></Scope>
<IOProtocol>ap_memory</IOProtocol>
<IOConfig></IOConfig>
<Dir>out</Dir>
<Bits>1</Bits>
<Attribute>control</Attribute>
</RtlPorts>
<RtlPorts>
<name>img_inT_we0</name>
<Object>img_inT</Object>
<Type>array</Type>
<Scope></Scope>
<IOProtocol>ap_memory</IOProtocol>
<IOConfig></IOConfig>
<Dir>out</Dir>
<Bits>1</Bits>
<Attribute>control</Attribute>
</RtlPorts>
<RtlPorts>
<name>img_inT_d0</name>
<Object>img_inT</Object>
<Type>array</Type>
<Scope></Scope>
<IOProtocol>ap_memory</IOProtocol>
<IOConfig></IOConfig>
<Dir>out</Dir>
<Bits>8</Bits>
<Attribute>data</Attribute>
</RtlPorts>
<RtlPorts>
<name>img_in_0_address0</name>
<Object>img_in_0</Object>
<Type>array</Type>
<Scope></Scope>
<IOProtocol>ap_memory</IOProtocol>
<IOConfig></IOConfig>
<Dir>out</Dir>
<Bits>3</Bits>
<Attribute>address</Attribute>
</RtlPorts>
<RtlPorts>
<name>img_in_0_ce0</name>
<Object>img_in_0</Object>
<Type>array</Type>
<Scope></Scope>
<IOProtocol>ap_memory</IOProtocol>
<IOConfig></IOConfig>
<Dir>out</Dir>
<Bits>1</Bits>
<Attribute>control</Attribute>
</RtlPorts>
<RtlPorts>
<name>img_in_0_q0</name>
<Object>img_in_0</Object>
<Type>array</Type>
<Scope></Scope>
<IOProtocol>ap_memory</IOProtocol>
<IOConfig></IOConfig>
<Dir>in</Dir>
<Bits>8</Bits>
<Attribute>data</Attribute>
</RtlPorts>
<RtlPorts>
<name>img_in_1_address0</name>
<Object>img_in_1</Object>
<Type>array</Type>
<Scope></Scope>
<IOProtocol>ap_memory</IOProtocol>
<IOConfig></IOConfig>
<Dir>out</Dir>
<Bits>3</Bits>
<Attribute>address</Attribute>
</RtlPorts>
<RtlPorts>
<name>img_in_1_ce0</name>
<Object>img_in_1</Object>
<Type>array</Type>
<Scope></Scope>
<IOProtocol>ap_memory</IOProtocol>
<IOConfig></IOConfig>
<Dir>out</Dir>
<Bits>1</Bits>
<Attribute>control</Attribute>
</RtlPorts>
<RtlPorts>
<name>img_in_1_q0</name>
<Object>img_in_1</Object>
<Type>array</Type>
<Scope></Scope>
<IOProtocol>ap_memory</IOProtocol>
<IOConfig></IOConfig>
<Dir>in</Dir>
<Bits>8</Bits>
<Attribute>data</Attribute>
</RtlPorts>
</InterfaceSummary>
</Module>
<Module>
<Name>conv2D0_Pipeline_readweights</Name>
<Loops>
<readweights></readweights>
</Loops>
<PerformanceEstimates>
<SummaryOfTimingAnalysis>
<TargetClockPeriod>10.00</TargetClockPeriod>
<ClockUncertainty>2.70</ClockUncertainty>
<EstimatedClockPeriod>6.625</EstimatedClockPeriod>
</SummaryOfTimingAnalysis>
<SummaryOfOverallLatency>
<Best-caseLatency>11</Best-caseLatency>
<Average-caseLatency>11</Average-caseLatency>
<Worst-caseLatency>11</Worst-caseLatency>
<Best-caseRealTimeLatency>0.110 us</Best-caseRealTimeLatency>
<Average-caseRealTimeLatency>0.110 us</Average-caseRealTimeLatency>
<Worst-caseRealTimeLatency>0.110 us</Worst-caseRealTimeLatency>
<PipelineInitiationInterval>11</PipelineInitiationInterval>
<PipelineType>no</PipelineType>
</SummaryOfOverallLatency>
<SummaryOfLoopLatency>
<readweights>
<Name>readweights</Name>
<Slack>7.30</Slack>
<TripCount>9</TripCount>
<Latency>9</Latency>
<AbsoluteTimeLatency>90.000 ns</AbsoluteTimeLatency>
<PipelineII>1</PipelineII>
<PipelineDepth>2</PipelineDepth>
<PipelineType>yes</PipelineType>
<InstanceList>
</InstanceList>
</readweights>
</SummaryOfLoopLatency>
<SummaryOfViolations>
<IssueType>-</IssueType>
<ViolationType>-</ViolationType>
<SourceLocation>conv2D0.cpp:23</SourceLocation>
<SummaryOfLoopViolations>
<readweights>
<Name>readweights</Name>
<IssueType>-</IssueType>
<ViolationType>-</ViolationType>
<SourceLocation>conv2D0.cpp:23</SourceLocation>
</readweights>
</SummaryOfLoopViolations>
</SummaryOfViolations>
</PerformanceEstimates>
<AreaEstimates>
<Resources>
<FF>22</FF>
<AVAIL_FF>35200</AVAIL_FF>
<UTIL_FF>~0</UTIL_FF>
<LUT>132</LUT>
<AVAIL_LUT>17600</AVAIL_LUT>
<UTIL_LUT>~0</UTIL_LUT>
<BRAM_18K>0</BRAM_18K>
<AVAIL_BRAM>120</AVAIL_BRAM>
<UTIL_BRAM>0</UTIL_BRAM>
<DSP>0</DSP>
<AVAIL_DSP>80</AVAIL_DSP>
<UTIL_DSP>0</UTIL_DSP>
<URAM>0</URAM>
<AVAIL_URAM>0</AVAIL_URAM>
<UTIL_URAM>0</UTIL_URAM>
</Resources>
</AreaEstimates>
<InterfaceSummary>
<RtlPorts>
<name>ap_clk</name>
<Object>conv2D0_Pipeline_readweights</Object>
<Type>return value</Type>
<Scope></Scope>
<IOProtocol>ap_ctrl_hs</IOProtocol>
<IOConfig></IOConfig>
<Dir>in</Dir>
<Bits>1</Bits>
<Attribute>control</Attribute>
</RtlPorts>
<RtlPorts>
<name>ap_rst</name>
<Object>conv2D0_Pipeline_readweights</Object>
<Type>return value</Type>
<Scope></Scope>
<IOProtocol>ap_ctrl_hs</IOProtocol>
<IOConfig></IOConfig>
<Dir>in</Dir>
<Bits>1</Bits>
<Attribute>control</Attribute>
</RtlPorts>
<RtlPorts>
<name>ap_start</name>
<Object>conv2D0_Pipeline_readweights</Object>
<Type>return value</Type>
<Scope></Scope>
<IOProtocol>ap_ctrl_hs</IOProtocol>
<IOConfig></IOConfig>
<Dir>in</Dir>
<Bits>1</Bits>
<Attribute>control</Attribute>
</RtlPorts>
<RtlPorts>
<name>ap_done</name>
<Object>conv2D0_Pipeline_readweights</Object>
<Type>return value</Type>
<Scope></Scope>
<IOProtocol>ap_ctrl_hs</IOProtocol>
<IOConfig></IOConfig>
<Dir>out</Dir>
<Bits>1</Bits>
<Attribute>control</Attribute>
</RtlPorts>
<RtlPorts>
<name>ap_idle</name>
<Object>conv2D0_Pipeline_readweights</Object>
<Type>return value</Type>
<Scope></Scope>
<IOProtocol>ap_ctrl_hs</IOProtocol>
<IOConfig></IOConfig>
<Dir>out</Dir>
<Bits>1</Bits>
<Attribute>control</Attribute>
</RtlPorts>
<RtlPorts>
<name>ap_ready</name>
<Object>conv2D0_Pipeline_readweights</Object>
<Type>return value</Type>
<Scope></Scope>
<IOProtocol>ap_ctrl_hs</IOProtocol>
<IOConfig></IOConfig>
<Dir>out</Dir>
<Bits>1</Bits>
<Attribute>control</Attribute>
</RtlPorts>
<RtlPorts>
<name>weightsT_1_address0</name>
<Object>weightsT_1</Object>
<Type>array</Type>
<Scope></Scope>
<IOProtocol>ap_memory</IOProtocol>
<IOConfig></IOConfig>
<Dir>out</Dir>
<Bits>3</Bits>
<Attribute>address</Attribute>
</RtlPorts>
<RtlPorts>
<name>weightsT_1_ce0</name>
<Object>weightsT_1</Object>
<Type>array</Type>
<Scope></Scope>
<IOProtocol>ap_memory</IOProtocol>
<IOConfig></IOConfig>
<Dir>out</Dir>
<Bits>1</Bits>
<Attribute>control</Attribute>
</RtlPorts>
<RtlPorts>
<name>weightsT_1_we0</name>
<Object>weightsT_1</Object>
<Type>array</Type>
<Scope></Scope>
<IOProtocol>ap_memory</IOProtocol>
<IOConfig></IOConfig>
<Dir>out</Dir>
<Bits>1</Bits>
<Attribute>control</Attribute>
</RtlPorts>
<RtlPorts>
<name>weightsT_1_d0</name>
<Object>weightsT_1</Object>
<Type>array</Type>
<Scope></Scope>
<IOProtocol>ap_memory</IOProtocol>
<IOConfig></IOConfig>
<Dir>out</Dir>
<Bits>8</Bits>
<Attribute>data</Attribute>
</RtlPorts>
<RtlPorts>
<name>weightsT_address0</name>
<Object>weightsT</Object>
<Type>array</Type>
<Scope></Scope>
<IOProtocol>ap_memory</IOProtocol>
<IOConfig></IOConfig>
<Dir>out</Dir>
<Bits>3</Bits>
<Attribute>address</Attribute>
</RtlPorts>
<RtlPorts>
<name>weightsT_ce0</name>
<Object>weightsT</Object>
<Type>array</Type>
<Scope></Scope>
<IOProtocol>ap_memory</IOProtocol>
<IOConfig></IOConfig>
<Dir>out</Dir>
<Bits>1</Bits>
<Attribute>control</Attribute>
</RtlPorts>
<RtlPorts>
<name>weightsT_we0</name>
<Object>weightsT</Object>
<Type>array</Type>
<Scope></Scope>
<IOProtocol>ap_memory</IOProtocol>
<IOConfig></IOConfig>
<Dir>out</Dir>
<Bits>1</Bits>
<Attribute>control</Attribute>
</RtlPorts>
<RtlPorts>
<name>weightsT_d0</name>
<Object>weightsT</Object>
<Type>array</Type>
<Scope></Scope>
<IOProtocol>ap_memory</IOProtocol>
<IOConfig></IOConfig>
<Dir>out</Dir>
<Bits>8</Bits>
<Attribute>data</Attribute>
</RtlPorts>
<RtlPorts>
<name>weights_0_address0</name>
<Object>weights_0</Object>
<Type>array</Type>
<Scope></Scope>
<IOProtocol>ap_memory</IOProtocol>
<IOConfig></IOConfig>
<Dir>out</Dir>
<Bits>3</Bits>
<Attribute>address</Attribute>
</RtlPorts>
<RtlPorts>
<name>weights_0_ce0</name>
<Object>weights_0</Object>
<Type>array</Type>
<Scope></Scope>
<IOProtocol>ap_memory</IOProtocol>
<IOConfig></IOConfig>
<Dir>out</Dir>
<Bits>1</Bits>
<Attribute>control</Attribute>
</RtlPorts>
<RtlPorts>
<name>weights_0_q0</name>
<Object>weights_0</Object>
<Type>array</Type>
<Scope></Scope>
<IOProtocol>ap_memory</IOProtocol>
<IOConfig></IOConfig>
<Dir>in</Dir>
<Bits>8</Bits>
<Attribute>data</Attribute>
</RtlPorts>
<RtlPorts>
<name>weights_1_address0</name>
<Object>weights_1</Object>
<Type>array</Type>
<Scope></Scope>
<IOProtocol>ap_memory</IOProtocol>
<IOConfig></IOConfig>
<Dir>out</Dir>
<Bits>3</Bits>
<Attribute>address</Attribute>
</RtlPorts>
<RtlPorts>
<name>weights_1_ce0</name>
<Object>weights_1</Object>
<Type>array</Type>
<Scope></Scope>
<IOProtocol>ap_memory</IOProtocol>
<IOConfig></IOConfig>
<Dir>out</Dir>
<Bits>1</Bits>
<Attribute>control</Attribute>
</RtlPorts>
<RtlPorts>
<name>weights_1_q0</name>
<Object>weights_1</Object>
<Type>array</Type>
<Scope></Scope>
<IOProtocol>ap_memory</IOProtocol>
<IOConfig></IOConfig>
<Dir>in</Dir>
<Bits>8</Bits>
<Attribute>data</Attribute>
</RtlPorts>
</InterfaceSummary>
</Module>
<Module>
<Name>conv2D0_Pipeline_loop_orow_loop_ocol</Name>
<Loops>
<loop_orow_loop_ocol></loop_orow_loop_ocol>
</Loops>
<PerformanceEstimates>
<SummaryOfTimingAnalysis>
<TargetClockPeriod>10.00</TargetClockPeriod>
<ClockUncertainty>2.70</ClockUncertainty>
<EstimatedClockPeriod>8.203</EstimatedClockPeriod>
</SummaryOfTimingAnalysis>
<SummaryOfOverallLatency>
<Best-caseLatency>11</Best-caseLatency>
<Average-caseLatency>11</Average-caseLatency>
<Worst-caseLatency>11</Worst-caseLatency>
<Best-caseRealTimeLatency>0.110 us</Best-caseRealTimeLatency>
<Average-caseRealTimeLatency>0.110 us</Average-caseRealTimeLatency>
<Worst-caseRealTimeLatency>0.110 us</Worst-caseRealTimeLatency>
<PipelineInitiationInterval>11</PipelineInitiationInterval>
<PipelineType>no</PipelineType>
</SummaryOfOverallLatency>
<SummaryOfLoopLatency>
<loop_orow_loop_ocol>
<Name>loop_orow_loop_ocol</Name>
<Slack>7.30</Slack>
<TripCount>4</TripCount>
<Latency>9</Latency>
<AbsoluteTimeLatency>90.000 ns</AbsoluteTimeLatency>
<PipelineII>1</PipelineII>
<PipelineDepth>7</PipelineDepth>
<PipelineType>yes</PipelineType>
<InstanceList>
</InstanceList>
</loop_orow_loop_ocol>
</SummaryOfLoopLatency>
<SummaryOfViolations>
<IssueType>Timing Violation</IssueType>
<ViolationType>-</ViolationType>
<SourceLocation>conv2D0.cpp:27</SourceLocation>
<SummaryOfLoopViolations>
<loop_orow_loop_ocol>
<Name>loop_orow_loop_ocol</Name>
<IssueType>-</IssueType>
<ViolationType>-</ViolationType>
<SourceLocation>conv2D0.cpp:26</SourceLocation>
</loop_orow_loop_ocol>
</SummaryOfLoopViolations>
</SummaryOfViolations>
</PerformanceEstimates>
<AreaEstimates>
<Resources>
<DSP>5</DSP>
<AVAIL_DSP>80</AVAIL_DSP>
<UTIL_DSP>6</UTIL_DSP>
<FF>368</FF>
<AVAIL_FF>35200</AVAIL_FF>
<UTIL_FF>1</UTIL_FF>
<LUT>496</LUT>
<AVAIL_LUT>17600</AVAIL_LUT>
<UTIL_LUT>2</UTIL_LUT>
<BRAM_18K>0</BRAM_18K>
<AVAIL_BRAM>120</AVAIL_BRAM>
<UTIL_BRAM>0</UTIL_BRAM>
<URAM>0</URAM>
<AVAIL_URAM>0</AVAIL_URAM>
<UTIL_URAM>0</UTIL_URAM>
</Resources>
</AreaEstimates>
<InterfaceSummary>
<RtlPorts>
<name>ap_clk</name>
<Object>conv2D0_Pipeline_loop_orow_loop_ocol</Object>
<Type>return value</Type>
<Scope></Scope>
<IOProtocol>ap_ctrl_hs</IOProtocol>
<IOConfig></IOConfig>
<Dir>in</Dir>
<Bits>1</Bits>
<Attribute>control</Attribute>
</RtlPorts>
<RtlPorts>
<name>ap_rst</name>
<Object>conv2D0_Pipeline_loop_orow_loop_ocol</Object>
<Type>return value</Type>
<Scope></Scope>
<IOProtocol>ap_ctrl_hs</IOProtocol>
<IOConfig></IOConfig>
<Dir>in</Dir>
<Bits>1</Bits>
<Attribute>control</Attribute>
</RtlPorts>
<RtlPorts>
<name>ap_start</name>
<Object>conv2D0_Pipeline_loop_orow_loop_ocol</Object>
<Type>return value</Type>
<Scope></Scope>
<IOProtocol>ap_ctrl_hs</IOProtocol>
<IOConfig></IOConfig>
<Dir>in</Dir>
<Bits>1</Bits>
<Attribute>control</Attribute>
</RtlPorts>
<RtlPorts>
<name>ap_done</name>
<Object>conv2D0_Pipeline_loop_orow_loop_ocol</Object>
<Type>return value</Type>
<Scope></Scope>
<IOProtocol>ap_ctrl_hs</IOProtocol>
<IOConfig></IOConfig>
<Dir>out</Dir>
<Bits>1</Bits>
<Attribute>control</Attribute>
</RtlPorts>
<RtlPorts>
<name>ap_idle</name>
<Object>conv2D0_Pipeline_loop_orow_loop_ocol</Object>
<Type>return value</Type>
<Scope></Scope>
<IOProtocol>ap_ctrl_hs</IOProtocol>
<IOConfig></IOConfig>
<Dir>out</Dir>
<Bits>1</Bits>
<Attribute>control</Attribute>
</RtlPorts>
<RtlPorts>
<name>ap_ready</name>
<Object>conv2D0_Pipeline_loop_orow_loop_ocol</Object>
<Type>return value</Type>
<Scope></Scope>
<IOProtocol>ap_ctrl_hs</IOProtocol>
<IOConfig></IOConfig>
<Dir>out</Dir>
<Bits>1</Bits>
<Attribute>control</Attribute>
</RtlPorts>
<RtlPorts>
<name>img_inT_address0</name>
<Object>img_inT</Object>
<Type>array</Type>
<Scope></Scope>
<IOProtocol>ap_memory</IOProtocol>
<IOConfig></IOConfig>
<Dir>out</Dir>
<Bits>3</Bits>
<Attribute>address</Attribute>
</RtlPorts>
<RtlPorts>
<name>img_inT_ce0</name>
<Object>img_inT</Object>
<Type>array</Type>
<Scope></Scope>
<IOProtocol>ap_memory</IOProtocol>
<IOConfig></IOConfig>
<Dir>out</Dir>
<Bits>1</Bits>
<Attribute>control</Attribute>
</RtlPorts>
<RtlPorts>
<name>img_inT_q0</name>
<Object>img_inT</Object>
<Type>array</Type>
<Scope></Scope>
<IOProtocol>ap_memory</IOProtocol>
<IOConfig></IOConfig>
<Dir>in</Dir>
<Bits>8</Bits>
<Attribute>data</Attribute>
</RtlPorts>
<RtlPorts>
<name>img_inT_address1</name>
<Object>img_inT</Object>
<Type>array</Type>
<Scope></Scope>
<IOProtocol>ap_memory</IOProtocol>
<IOConfig></IOConfig>
<Dir>out</Dir>
<Bits>3</Bits>
<Attribute>address</Attribute>
</RtlPorts>
<RtlPorts>
<name>img_inT_ce1</name>
<Object>img_inT</Object>
<Type>array</Type>
<Scope></Scope>
<IOProtocol>ap_memory</IOProtocol>
<IOConfig></IOConfig>
<Dir>out</Dir>
<Bits>1</Bits>
<Attribute>control</Attribute>
</RtlPorts>
<RtlPorts>
<name>img_inT_q1</name>
<Object>img_inT</Object>
<Type>array</Type>
<Scope></Scope>
<IOProtocol>ap_memory</IOProtocol>
<IOConfig></IOConfig>
<Dir>in</Dir>
<Bits>8</Bits>
<Attribute>data</Attribute>
</RtlPorts>
<RtlPorts>
<name>img_inT_address2</name>
<Object>img_inT</Object>
<Type>array</Type>
<Scope></Scope>
<IOProtocol>ap_memory</IOProtocol>
<IOConfig></IOConfig>
<Dir>out</Dir>
<Bits>3</Bits>
<Attribute>address</Attribute>
</RtlPorts>
<RtlPorts>
<name>img_inT_ce2</name>
<Object>img_inT</Object>
<Type>array</Type>
<Scope></Scope>
<IOProtocol>ap_memory</IOProtocol>
<IOConfig></IOConfig>
<Dir>out</Dir>
<Bits>1</Bits>
<Attribute>control</Attribute>
</RtlPorts>
<RtlPorts>
<name>img_inT_q2</name>
<Object>img_inT</Object>
<Type>array</Type>
<Scope></Scope>
<IOProtocol>ap_memory</IOProtocol>
<IOConfig></IOConfig>
<Dir>in</Dir>
<Bits>8</Bits>
<Attribute>data</Attribute>
</RtlPorts>
<RtlPorts>
<name>img_inT_address3</name>
<Object>img_inT</Object>
<Type>array</Type>
<Scope></Scope>
<IOProtocol>ap_memory</IOProtocol>
<IOConfig></IOConfig>
<Dir>out</Dir>
<Bits>3</Bits>
<Attribute>address</Attribute>
</RtlPorts>
<RtlPorts>
<name>img_inT_ce3</name>
<Object>img_inT</Object>
<Type>array</Type>
<Scope></Scope>
<IOProtocol>ap_memory</IOProtocol>
<IOConfig></IOConfig>
<Dir>out</Dir>
<Bits>1</Bits>
<Attribute>control</Attribute>
</RtlPorts>
<RtlPorts>
<name>img_inT_q3</name>
<Object>img_inT</Object>
<Type>array</Type>
<Scope></Scope>
<IOProtocol>ap_memory</IOProtocol>
<IOConfig></IOConfig>
<Dir>in</Dir>
<Bits>8</Bits>
<Attribute>data</Attribute>
</RtlPorts>
<RtlPorts>
<name>img_inT_address4</name>
<Object>img_inT</Object>
<Type>array</Type>
<Scope></Scope>
<IOProtocol>ap_memory</IOProtocol>
<IOConfig></IOConfig>
<Dir>out</Dir>
<Bits>3</Bits>
<Attribute>address</Attribute>
</RtlPorts>
<RtlPorts>
<name>img_inT_ce4</name>
<Object>img_inT</Object>
<Type>array</Type>
<Scope></Scope>
<IOProtocol>ap_memory</IOProtocol>
<IOConfig></IOConfig>
<Dir>out</Dir>
<Bits>1</Bits>
<Attribute>control</Attribute>
</RtlPorts>
<RtlPorts>
<name>img_inT_q4</name>
<Object>img_inT</Object>
<Type>array</Type>
<Scope></Scope>
<IOProtocol>ap_memory</IOProtocol>
<IOConfig></IOConfig>
<Dir>in</Dir>
<Bits>8</Bits>
<Attribute>data</Attribute>
</RtlPorts>
<RtlPorts>
<name>img_inT_address5</name>
<Object>img_inT</Object>
<Type>array</Type>
<Scope></Scope>
<IOProtocol>ap_memory</IOProtocol>
<IOConfig></IOConfig>
<Dir>out</Dir>
<Bits>3</Bits>
<Attribute>address</Attribute>
</RtlPorts>
<RtlPorts>
<name>img_inT_ce5</name>
<Object>img_inT</Object>
<Type>array</Type>
<Scope></Scope>
<IOProtocol>ap_memory</IOProtocol>
<IOConfig></IOConfig>
<Dir>out</Dir>
<Bits>1</Bits>
<Attribute>control</Attribute>
</RtlPorts>
<RtlPorts>
<name>img_inT_q5</name>
<Object>img_inT</Object>
<Type>array</Type>
<Scope></Scope>
<IOProtocol>ap_memory</IOProtocol>
<IOConfig></IOConfig>
<Dir>in</Dir>
<Bits>8</Bits>
<Attribute>data</Attribute>
</RtlPorts>
<RtlPorts>
<name>img_inT_1_address0</name>
<Object>img_inT_1</Object>
<Type>array</Type>
<Scope></Scope>
<IOProtocol>ap_memory</IOProtocol>
<IOConfig></IOConfig>
<Dir>out</Dir>
<Bits>3</Bits>
<Attribute>address</Attribute>
</RtlPorts>
<RtlPorts>
<name>img_inT_1_ce0</name>
<Object>img_inT_1</Object>
<Type>array</Type>
<Scope></Scope>
<IOProtocol>ap_memory</IOProtocol>
<IOConfig></IOConfig>
<Dir>out</Dir>
<Bits>1</Bits>
<Attribute>control</Attribute>
</RtlPorts>
<RtlPorts>
<name>img_inT_1_q0</name>
<Object>img_inT_1</Object>
<Type>array</Type>
<Scope></Scope>
<IOProtocol>ap_memory</IOProtocol>
<IOConfig></IOConfig>
<Dir>in</Dir>
<Bits>8</Bits>
<Attribute>data</Attribute>
</RtlPorts>
<RtlPorts>
<name>img_inT_1_address1</name>
<Object>img_inT_1</Object>
<Type>array</Type>
<Scope></Scope>
<IOProtocol>ap_memory</IOProtocol>
<IOConfig></IOConfig>
<Dir>out</Dir>
<Bits>3</Bits>
<Attribute>address</Attribute>
</RtlPorts>
<RtlPorts>
<name>img_inT_1_ce1</name>
<Object>img_inT_1</Object>
<Type>array</Type>
<Scope></Scope>
<IOProtocol>ap_memory</IOProtocol>
<IOConfig></IOConfig>
<Dir>out</Dir>
<Bits>1</Bits>
<Attribute>control</Attribute>
</RtlPorts>
<RtlPorts>
<name>img_inT_1_q1</name>
<Object>img_inT_1</Object>
<Type>array</Type>
<Scope></Scope>
<IOProtocol>ap_memory</IOProtocol>
<IOConfig></IOConfig>
<Dir>in</Dir>
<Bits>8</Bits>
<Attribute>data</Attribute>
</RtlPorts>
<RtlPorts>
<name>img_inT_1_address2</name>
<Object>img_inT_1</Object>
<Type>array</Type>
<Scope></Scope>
<IOProtocol>ap_memory</IOProtocol>
<IOConfig></IOConfig>
<Dir>out</Dir>
<Bits>3</Bits>
<Attribute>address</Attribute>
</RtlPorts>
<RtlPorts>
<name>img_inT_1_ce2</name>
<Object>img_inT_1</Object>
<Type>array</Type>
<Scope></Scope>
<IOProtocol>ap_memory</IOProtocol>
<IOConfig></IOConfig>
<Dir>out</Dir>
<Bits>1</Bits>
<Attribute>control</Attribute>
</RtlPorts>
<RtlPorts>
<name>img_inT_1_q2</name>
<Object>img_inT_1</Object>
<Type>array</Type>
<Scope></Scope>
<IOProtocol>ap_memory</IOProtocol>
<IOConfig></IOConfig>
<Dir>in</Dir>
<Bits>8</Bits>
<Attribute>data</Attribute>
</RtlPorts>
<RtlPorts>
<name>img_inT_1_address3</name>
<Object>img_inT_1</Object>
<Type>array</Type>
<Scope></Scope>
<IOProtocol>ap_memory</IOProtocol>
<IOConfig></IOConfig>
<Dir>out</Dir>
<Bits>3</Bits>
<Attribute>address</Attribute>
</RtlPorts>
<RtlPorts>
<name>img_inT_1_ce3</name>
<Object>img_inT_1</Object>
<Type>array</Type>
<Scope></Scope>
<IOProtocol>ap_memory</IOProtocol>
<IOConfig></IOConfig>
<Dir>out</Dir>
<Bits>1</Bits>
<Attribute>control</Attribute>
</RtlPorts>
<RtlPorts>
<name>img_inT_1_q3</name>
<Object>img_inT_1</Object>
<Type>array</Type>
<Scope></Scope>
<IOProtocol>ap_memory</IOProtocol>
<IOConfig></IOConfig>
<Dir>in</Dir>
<Bits>8</Bits>
<Attribute>data</Attribute>
</RtlPorts>
<RtlPorts>
<name>img_inT_1_address4</name>
<Object>img_inT_1</Object>
<Type>array</Type>
<Scope></Scope>
<IOProtocol>ap_memory</IOProtocol>
<IOConfig></IOConfig>
<Dir>out</Dir>
<Bits>3</Bits>
<Attribute>address</Attribute>
</RtlPorts>
<RtlPorts>
<name>img_inT_1_ce4</name>
<Object>img_inT_1</Object>
<Type>array</Type>
<Scope></Scope>
<IOProtocol>ap_memory</IOProtocol>
<IOConfig></IOConfig>
<Dir>out</Dir>
<Bits>1</Bits>
<Attribute>control</Attribute>
</RtlPorts>
<RtlPorts>
<name>img_inT_1_q4</name>
<Object>img_inT_1</Object>
<Type>array</Type>
<Scope></Scope>
<IOProtocol>ap_memory</IOProtocol>
<IOConfig></IOConfig>
<Dir>in</Dir>
<Bits>8</Bits>
<Attribute>data</Attribute>
</RtlPorts>
<RtlPorts>
<name>img_inT_1_address5</name>
<Object>img_inT_1</Object>
<Type>array</Type>
<Scope></Scope>
<IOProtocol>ap_memory</IOProtocol>
<IOConfig></IOConfig>
<Dir>out</Dir>
<Bits>3</Bits>
<Attribute>address</Attribute>
</RtlPorts>
<RtlPorts>
<name>img_inT_1_ce5</name>
<Object>img_inT_1</Object>
<Type>array</Type>
<Scope></Scope>
<IOProtocol>ap_memory</IOProtocol>
<IOConfig></IOConfig>
<Dir>out</Dir>
<Bits>1</Bits>
<Attribute>control</Attribute>
</RtlPorts>
<RtlPorts>
<name>img_inT_1_q5</name>
<Object>img_inT_1</Object>
<Type>array</Type>
<Scope></Scope>
<IOProtocol>ap_memory</IOProtocol>
<IOConfig></IOConfig>
<Dir>in</Dir>
<Bits>8</Bits>
<Attribute>data</Attribute>
</RtlPorts>
<RtlPorts>
<name>weightsT_load</name>
<Object>weightsT_load</Object>
<Type>scalar</Type>
<Scope></Scope>
<IOProtocol>ap_none</IOProtocol>
<IOConfig></IOConfig>
<Dir>in</Dir>
<Bits>8</Bits>
<Attribute>data</Attribute>
</RtlPorts>
<RtlPorts>
<name>weightsT_load_1</name>
<Object>weightsT_load_1</Object>
<Type>scalar</Type>
<Scope></Scope>
<IOProtocol>ap_none</IOProtocol>
<IOConfig></IOConfig>
<Dir>in</Dir>
<Bits>8</Bits>
<Attribute>data</Attribute>
</RtlPorts>
<RtlPorts>
<name>weightsT_load_2</name>
<Object>weightsT_load_2</Object>
<Type>scalar</Type>
<Scope></Scope>
<IOProtocol>ap_none</IOProtocol>
<IOConfig></IOConfig>
<Dir>in</Dir>
<Bits>8</Bits>
<Attribute>data</Attribute>
</RtlPorts>
<RtlPorts>
<name>weightsT_load_3</name>
<Object>weightsT_load_3</Object>
<Type>scalar</Type>
<Scope></Scope>
<IOProtocol>ap_none</IOProtocol>
<IOConfig></IOConfig>
<Dir>in</Dir>
<Bits>8</Bits>
<Attribute>data</Attribute>
</RtlPorts>
<RtlPorts>
<name>weightsT_load_4</name>
<Object>weightsT_load_4</Object>
<Type>scalar</Type>
<Scope></Scope>
<IOProtocol>ap_none</IOProtocol>
<IOConfig></IOConfig>
<Dir>in</Dir>
<Bits>8</Bits>
<Attribute>data</Attribute>
</RtlPorts>
<RtlPorts>
<name>weightsT_1_load</name>
<Object>weightsT_1_load</Object>
<Type>scalar</Type>
<Scope></Scope>
<IOProtocol>ap_none</IOProtocol>
<IOConfig></IOConfig>
<Dir>in</Dir>
<Bits>8</Bits>
<Attribute>data</Attribute>
</RtlPorts>
<RtlPorts>
<name>weightsT_1_load_1</name>
<Object>weightsT_1_load_1</Object>
<Type>scalar</Type>
<Scope></Scope>
<IOProtocol>ap_none</IOProtocol>
<IOConfig></IOConfig>
<Dir>in</Dir>
<Bits>8</Bits>
<Attribute>data</Attribute>
</RtlPorts>
<RtlPorts>
<name>weightsT_1_load_2</name>
<Object>weightsT_1_load_2</Object>
<Type>scalar</Type>
<Scope></Scope>
<IOProtocol>ap_none</IOProtocol>
<IOConfig></IOConfig>
<Dir>in</Dir>
<Bits>8</Bits>
<Attribute>data</Attribute>
</RtlPorts>
<RtlPorts>
<name>weightsT_1_load_3</name>
<Object>weightsT_1_load_3</Object>
<Type>scalar</Type>
<Scope></Scope>
<IOProtocol>ap_none</IOProtocol>
<IOConfig></IOConfig>
<Dir>in</Dir>
<Bits>8</Bits>
<Attribute>data</Attribute>
</RtlPorts>
<RtlPorts>
<name>img_outT_1_1_load15_out</name>
<Object>img_outT_1_1_load15_out</Object>
<Type>pointer</Type>
<Scope></Scope>
<IOProtocol>ap_vld</IOProtocol>
<IOConfig></IOConfig>
<Dir>out</Dir>
<Bits>8</Bits>
<Attribute>data</Attribute>
</RtlPorts>
<RtlPorts>
<name>img_outT_1_1_load15_out_ap_vld</name>
<Object>img_outT_1_1_load15_out</Object>
<Type>pointer</Type>
<Scope></Scope>
<IOProtocol>ap_vld</IOProtocol>
<IOConfig></IOConfig>
<Dir>out</Dir>
<Bits>1</Bits>
<Attribute>control</Attribute>
</RtlPorts>
<RtlPorts>
<name>img_outT_0_1_load11_out</name>
<Object>img_outT_0_1_load11_out</Object>
<Type>pointer</Type>
<Scope></Scope>
<IOProtocol>ap_vld</IOProtocol>
<IOConfig></IOConfig>
<Dir>out</Dir>
<Bits>8</Bits>
<Attribute>data</Attribute>
</RtlPorts>
<RtlPorts>
<name>img_outT_0_1_load11_out_ap_vld</name>
<Object>img_outT_0_1_load11_out</Object>
<Type>pointer</Type>
<Scope></Scope>
<IOProtocol>ap_vld</IOProtocol>
<IOConfig></IOConfig>
<Dir>out</Dir>
<Bits>1</Bits>
<Attribute>control</Attribute>
</RtlPorts>
<RtlPorts>
<name>img_outT_1_load7_out</name>
<Object>img_outT_1_load7_out</Object>
<Type>pointer</Type>
<Scope></Scope>
<IOProtocol>ap_vld</IOProtocol>
<IOConfig></IOConfig>
<Dir>out</Dir>
<Bits>8</Bits>
<Attribute>data</Attribute>
</RtlPorts>
<RtlPorts>
<name>img_outT_1_load7_out_ap_vld</name>
<Object>img_outT_1_load7_out</Object>
<Type>pointer</Type>
<Scope></Scope>
<IOProtocol>ap_vld</IOProtocol>
<IOConfig></IOConfig>
<Dir>out</Dir>
<Bits>1</Bits>
<Attribute>control</Attribute>
</RtlPorts>
<RtlPorts>
<name>img_outT_0_load3_out</name>
<Object>img_outT_0_load3_out</Object>
<Type>pointer</Type>
<Scope></Scope>
<IOProtocol>ap_vld</IOProtocol>
<IOConfig></IOConfig>
<Dir>out</Dir>
<Bits>8</Bits>
<Attribute>data</Attribute>
</RtlPorts>
<RtlPorts>
<name>img_outT_0_load3_out_ap_vld</name>
<Object>img_outT_0_load3_out</Object>
<Type>pointer</Type>
<Scope></Scope>
<IOProtocol>ap_vld</IOProtocol>
<IOConfig></IOConfig>
<Dir>out</Dir>
<Bits>1</Bits>
<Attribute>control</Attribute>
</RtlPorts>
</InterfaceSummary>
</Module>
<Module>
<Name>conv2D0_Pipeline_writeImg</Name>
<Loops>
<writeImg></writeImg>
</Loops>
<PerformanceEstimates>
<SummaryOfTimingAnalysis>
<TargetClockPeriod>10.00</TargetClockPeriod>
<ClockUncertainty>2.70</ClockUncertainty>
<EstimatedClockPeriod>6.406</EstimatedClockPeriod>
</SummaryOfTimingAnalysis>
<SummaryOfOverallLatency>
<Best-caseLatency>6</Best-caseLatency>
<Average-caseLatency>6</Average-caseLatency>
<Worst-caseLatency>6</Worst-caseLatency>
<Best-caseRealTimeLatency>60.000 ns</Best-caseRealTimeLatency>
<Average-caseRealTimeLatency>60.000 ns</Average-caseRealTimeLatency>
<Worst-caseRealTimeLatency>60.000 ns</Worst-caseRealTimeLatency>
<PipelineInitiationInterval>6</PipelineInitiationInterval>
<PipelineType>no</PipelineType>
</SummaryOfOverallLatency>
<SummaryOfLoopLatency>
<writeImg>
<Name>writeImg</Name>
<Slack>7.30</Slack>
<TripCount>4</TripCount>
<Latency>4</Latency>
<AbsoluteTimeLatency>40.000 ns</AbsoluteTimeLatency>
<PipelineII>1</PipelineII>
<PipelineDepth>1</PipelineDepth>
<PipelineType>yes</PipelineType>
<InstanceList>
</InstanceList>
</writeImg>
</SummaryOfLoopLatency>
<SummaryOfViolations>
<IssueType>-</IssueType>
<ViolationType>-</ViolationType>
<SourceLocation>conv2D0.cpp:40</SourceLocation>
<SummaryOfLoopViolations>
<writeImg>
<Name>writeImg</Name>
<IssueType>-</IssueType>
<ViolationType>-</ViolationType>
<SourceLocation>conv2D0.cpp:40</SourceLocation>
</writeImg>
</SummaryOfLoopViolations>
</SummaryOfViolations>
</PerformanceEstimates>
<AreaEstimates>
<Resources>
<FF>5</FF>
<AVAIL_FF>35200</AVAIL_FF>
<UTIL_FF>~0</UTIL_FF>
<LUT>75</LUT>
<AVAIL_LUT>17600</AVAIL_LUT>
<UTIL_LUT>~0</UTIL_LUT>
<BRAM_18K>0</BRAM_18K>
<AVAIL_BRAM>120</AVAIL_BRAM>
<UTIL_BRAM>0</UTIL_BRAM>
<DSP>0</DSP>
<AVAIL_DSP>80</AVAIL_DSP>
<UTIL_DSP>0</UTIL_DSP>
<URAM>0</URAM>
<AVAIL_URAM>0</AVAIL_URAM>
<UTIL_URAM>0</UTIL_URAM>
</Resources>
</AreaEstimates>
<InterfaceSummary>
<RtlPorts>
<name>ap_clk</name>
<Object>conv2D0_Pipeline_writeImg</Object>
<Type>return value</Type>
<Scope></Scope>
<IOProtocol>ap_ctrl_hs</IOProtocol>
<IOConfig></IOConfig>
<Dir>in</Dir>
<Bits>1</Bits>
<Attribute>control</Attribute>
</RtlPorts>
<RtlPorts>
<name>ap_rst</name>
<Object>conv2D0_Pipeline_writeImg</Object>
<Type>return value</Type>
<Scope></Scope>
<IOProtocol>ap_ctrl_hs</IOProtocol>
<IOConfig></IOConfig>
<Dir>in</Dir>
<Bits>1</Bits>
<Attribute>control</Attribute>
</RtlPorts>
<RtlPorts>
<name>ap_start</name>
<Object>conv2D0_Pipeline_writeImg</Object>
<Type>return value</Type>
<Scope></Scope>
<IOProtocol>ap_ctrl_hs</IOProtocol>
<IOConfig></IOConfig>
<Dir>in</Dir>
<Bits>1</Bits>
<Attribute>control</Attribute>
</RtlPorts>
<RtlPorts>
<name>ap_done</name>
<Object>conv2D0_Pipeline_writeImg</Object>
<Type>return value</Type>
<Scope></Scope>
<IOProtocol>ap_ctrl_hs</IOProtocol>
<IOConfig></IOConfig>
<Dir>out</Dir>
<Bits>1</Bits>
<Attribute>control</Attribute>
</RtlPorts>
<RtlPorts>
<name>ap_idle</name>
<Object>conv2D0_Pipeline_writeImg</Object>
<Type>return value</Type>
<Scope></Scope>
<IOProtocol>ap_ctrl_hs</IOProtocol>
<IOConfig></IOConfig>
<Dir>out</Dir>
<Bits>1</Bits>
<Attribute>control</Attribute>
</RtlPorts>
<RtlPorts>
<name>ap_ready</name>
<Object>conv2D0_Pipeline_writeImg</Object>
<Type>return value</Type>
<Scope></Scope>
<IOProtocol>ap_ctrl_hs</IOProtocol>
<IOConfig></IOConfig>
<Dir>out</Dir>
<Bits>1</Bits>
<Attribute>control</Attribute>
</RtlPorts>
<RtlPorts>
<name>img_out_0_address0</name>
<Object>img_out_0</Object>
<Type>array</Type>
<Scope></Scope>
<IOProtocol>ap_memory</IOProtocol>
<IOConfig></IOConfig>
<Dir>out</Dir>
<Bits>1</Bits>
<Attribute>address</Attribute>
</RtlPorts>
<RtlPorts>
<name>img_out_0_ce0</name>
<Object>img_out_0</Object>
<Type>array</Type>
<Scope></Scope>
<IOProtocol>ap_memory</IOProtocol>
<IOConfig></IOConfig>
<Dir>out</Dir>
<Bits>1</Bits>
<Attribute>control</Attribute>
</RtlPorts>
<RtlPorts>
<name>img_out_0_we0</name>
<Object>img_out_0</Object>
<Type>array</Type>
<Scope></Scope>
<IOProtocol>ap_memory</IOProtocol>
<IOConfig></IOConfig>
<Dir>out</Dir>
<Bits>1</Bits>
<Attribute>control</Attribute>
</RtlPorts>
<RtlPorts>
<name>img_out_0_d0</name>
<Object>img_out_0</Object>
<Type>array</Type>
<Scope></Scope>
<IOProtocol>ap_memory</IOProtocol>
<IOConfig></IOConfig>
<Dir>out</Dir>
<Bits>8</Bits>
<Attribute>data</Attribute>
</RtlPorts>
<RtlPorts>
<name>img_out_1_address0</name>
<Object>img_out_1</Object>
<Type>array</Type>
<Scope></Scope>
<IOProtocol>ap_memory</IOProtocol>
<IOConfig></IOConfig>
<Dir>out</Dir>
<Bits>1</Bits>
<Attribute>address</Attribute>
</RtlPorts>
<RtlPorts>
<name>img_out_1_ce0</name>
<Object>img_out_1</Object>
<Type>array</Type>
<Scope></Scope>
<IOProtocol>ap_memory</IOProtocol>
<IOConfig></IOConfig>
<Dir>out</Dir>
<Bits>1</Bits>
<Attribute>control</Attribute>
</RtlPorts>
<RtlPorts>
<name>img_out_1_we0</name>
<Object>img_out_1</Object>
<Type>array</Type>
<Scope></Scope>
<IOProtocol>ap_memory</IOProtocol>
<IOConfig></IOConfig>
<Dir>out</Dir>
<Bits>1</Bits>
<Attribute>control</Attribute>
</RtlPorts>
<RtlPorts>
<name>img_out_1_d0</name>
<Object>img_out_1</Object>
<Type>array</Type>
<Scope></Scope>
<IOProtocol>ap_memory</IOProtocol>
<IOConfig></IOConfig>
<Dir>out</Dir>
<Bits>8</Bits>
<Attribute>data</Attribute>
</RtlPorts>
<RtlPorts>
<name>img_outT_1_load7_reload</name>
<Object>img_outT_1_load7_reload</Object>
<Type>scalar</Type>
<Scope></Scope>
<IOProtocol>ap_none</IOProtocol>
<IOConfig></IOConfig>
<Dir>in</Dir>
<Bits>8</Bits>
<Attribute>data</Attribute>
</RtlPorts>
<RtlPorts>
<name>img_outT_0_load3_reload</name>
<Object>img_outT_0_load3_reload</Object>
<Type>scalar</Type>
<Scope></Scope>
<IOProtocol>ap_none</IOProtocol>
<IOConfig></IOConfig>
<Dir>in</Dir>
<Bits>8</Bits>
<Attribute>data</Attribute>
</RtlPorts>
<RtlPorts>
<name>img_outT_1_1_load15_reload</name>
<Object>img_outT_1_1_load15_reload</Object>
<Type>scalar</Type>
<Scope></Scope>
<IOProtocol>ap_none</IOProtocol>
<IOConfig></IOConfig>
<Dir>in</Dir>
<Bits>8</Bits>
<Attribute>data</Attribute>
</RtlPorts>
<RtlPorts>
<name>img_outT_0_1_load11_reload</name>
<Object>img_outT_0_1_load11_reload</Object>
<Type>scalar</Type>
<Scope></Scope>
<IOProtocol>ap_none</IOProtocol>
<IOConfig></IOConfig>
<Dir>in</Dir>
<Bits>8</Bits>
<Attribute>data</Attribute>
</RtlPorts>
</InterfaceSummary>
</Module>
<Module>
<Name>conv2D0</Name>
<PerformanceEstimates>
<SummaryOfTimingAnalysis>
<TargetClockPeriod>10.00</TargetClockPeriod>
<ClockUncertainty>2.70</ClockUncertainty>
<EstimatedClockPeriod>8.203</EstimatedClockPeriod>
</SummaryOfTimingAnalysis>
<SummaryOfOverallLatency>
<Best-caseLatency>43</Best-caseLatency>
<Average-caseLatency>43</Average-caseLatency>
<Worst-caseLatency>43</Worst-caseLatency>
<Best-caseRealTimeLatency>0.430 us</Best-caseRealTimeLatency>
<Average-caseRealTimeLatency>0.430 us</Average-caseRealTimeLatency>
<Worst-caseRealTimeLatency>0.430 us</Worst-caseRealTimeLatency>
<PipelineInitiationInterval>44</PipelineInitiationInterval>
<PipelineType>no</PipelineType>
</SummaryOfOverallLatency>
<SummaryOfViolations>
<IssueType>-</IssueType>
<ViolationType>-</ViolationType>
<SourceLocation>conv2D0.cpp:7</SourceLocation>
</SummaryOfViolations>
</PerformanceEstimates>
<AreaEstimates>
<Resources>
<BRAM_18K>0</BRAM_18K>
<AVAIL_BRAM>120</AVAIL_BRAM>
<UTIL_BRAM>0</UTIL_BRAM>
<DSP>5</DSP>
<AVAIL_DSP>80</AVAIL_DSP>
<UTIL_DSP>6</UTIL_DSP>
<FF>623</FF>
<AVAIL_FF>35200</AVAIL_FF>
<UTIL_FF>1</UTIL_FF>
<LUT>1118</LUT>
<AVAIL_LUT>17600</AVAIL_LUT>
<UTIL_LUT>6</UTIL_LUT>
<URAM>0</URAM>
<AVAIL_URAM>0</AVAIL_URAM>
<UTIL_URAM>0</UTIL_URAM>
</Resources>
</AreaEstimates>
<InterfaceSummary>
<RtlPorts>
<name>ap_clk</name>
<Object>conv2D0</Object>
<Type>return value</Type>
<Scope></Scope>
<IOProtocol>ap_ctrl_hs</IOProtocol>
<IOConfig></IOConfig>
<Dir>in</Dir>
<Bits>1</Bits>
<Attribute>control</Attribute>
</RtlPorts>
<RtlPorts>
<name>ap_rst</name>
<Object>conv2D0</Object>
<Type>return value</Type>
<Scope></Scope>
<IOProtocol>ap_ctrl_hs</IOProtocol>
<IOConfig></IOConfig>
<Dir>in</Dir>
<Bits>1</Bits>
<Attribute>control</Attribute>
</RtlPorts>
<RtlPorts>
<name>ap_start</name>
<Object>conv2D0</Object>
<Type>return value</Type>
<Scope></Scope>
<IOProtocol>ap_ctrl_hs</IOProtocol>
<IOConfig></IOConfig>
<Dir>in</Dir>
<Bits>1</Bits>
<Attribute>control</Attribute>
</RtlPorts>
<RtlPorts>
<name>ap_done</name>
<Object>conv2D0</Object>
<Type>return value</Type>
<Scope></Scope>
<IOProtocol>ap_ctrl_hs</IOProtocol>
<IOConfig></IOConfig>
<Dir>out</Dir>
<Bits>1</Bits>
<Attribute>control</Attribute>
</RtlPorts>
<RtlPorts>
<name>ap_idle</name>
<Object>conv2D0</Object>
<Type>return value</Type>
<Scope></Scope>
<IOProtocol>ap_ctrl_hs</IOProtocol>
<IOConfig></IOConfig>
<Dir>out</Dir>
<Bits>1</Bits>
<Attribute>control</Attribute>
</RtlPorts>
<RtlPorts>
<name>ap_ready</name>
<Object>conv2D0</Object>
<Type>return value</Type>
<Scope></Scope>
<IOProtocol>ap_ctrl_hs</IOProtocol>
<IOConfig></IOConfig>
<Dir>out</Dir>
<Bits>1</Bits>
<Attribute>control</Attribute>
</RtlPorts>
<RtlPorts>
<name>img_in_0_address0</name>
<Object>img_in_0</Object>
<Type>array</Type>
<Scope></Scope>
<IOProtocol>ap_memory</IOProtocol>
<IOConfig></IOConfig>
<Dir>out</Dir>
<Bits>3</Bits>
<Attribute>address</Attribute>
<CType>int</CType>
</RtlPorts>
<RtlPorts>
<name>img_in_0_ce0</name>
<Object>img_in_0</Object>
<Type>array</Type>
<Scope></Scope>
<IOProtocol>ap_memory</IOProtocol>
<IOConfig></IOConfig>
<Dir>out</Dir>
<Bits>1</Bits>
<Attribute>control</Attribute>
<CType>int</CType>
</RtlPorts>
<RtlPorts>
<name>img_in_0_q0</name>
<Object>img_in_0</Object>
<Type>array</Type>
<Scope></Scope>
<IOProtocol>ap_memory</IOProtocol>
<IOConfig></IOConfig>
<Dir>in</Dir>
<Bits>8</Bits>
<Attribute>data</Attribute>
<CType>int</CType>
</RtlPorts>
<RtlPorts>
<name>img_in_1_address0</name>
<Object>img_in_1</Object>
<Type>array</Type>
<Scope></Scope>
<IOProtocol>ap_memory</IOProtocol>
<IOConfig></IOConfig>
<Dir>out</Dir>
<Bits>3</Bits>
<Attribute>address</Attribute>
<CType>int</CType>
</RtlPorts>
<RtlPorts>
<name>img_in_1_ce0</name>
<Object>img_in_1</Object>
<Type>array</Type>
<Scope></Scope>
<IOProtocol>ap_memory</IOProtocol>
<IOConfig></IOConfig>
<Dir>out</Dir>
<Bits>1</Bits>
<Attribute>control</Attribute>
<CType>int</CType>
</RtlPorts>
<RtlPorts>
<name>img_in_1_q0</name>
<Object>img_in_1</Object>
<Type>array</Type>
<Scope></Scope>
<IOProtocol>ap_memory</IOProtocol>
<IOConfig></IOConfig>
<Dir>in</Dir>
<Bits>8</Bits>
<Attribute>data</Attribute>
<CType>int</CType>
</RtlPorts>
<RtlPorts>
<name>img_out_0_address0</name>
<Object>img_out_0</Object>
<Type>array</Type>
<Scope></Scope>
<IOProtocol>ap_memory</IOProtocol>
<IOConfig></IOConfig>
<Dir>out</Dir>
<Bits>1</Bits>
<Attribute>address</Attribute>
<CType>int</CType>
</RtlPorts>
<RtlPorts>
<name>img_out_0_ce0</name>
<Object>img_out_0</Object>
<Type>array</Type>
<Scope></Scope>
<IOProtocol>ap_memory</IOProtocol>
<IOConfig></IOConfig>
<Dir>out</Dir>
<Bits>1</Bits>
<Attribute>control</Attribute>
<CType>int</CType>
</RtlPorts>
<RtlPorts>
<name>img_out_0_we0</name>
<Object>img_out_0</Object>
<Type>array</Type>
<Scope></Scope>
<IOProtocol>ap_memory</IOProtocol>
<IOConfig></IOConfig>
<Dir>out</Dir>
<Bits>1</Bits>
<Attribute>control</Attribute>
<CType>int</CType>
</RtlPorts>
<RtlPorts>
<name>img_out_0_d0</name>
<Object>img_out_0</Object>
<Type>array</Type>
<Scope></Scope>
<IOProtocol>ap_memory</IOProtocol>
<IOConfig></IOConfig>
<Dir>out</Dir>
<Bits>8</Bits>
<Attribute>data</Attribute>
<CType>int</CType>
</RtlPorts>
<RtlPorts>
<name>img_out_1_address0</name>
<Object>img_out_1</Object>
<Type>array</Type>
<Scope></Scope>
<IOProtocol>ap_memory</IOProtocol>
<IOConfig></IOConfig>
<Dir>out</Dir>
<Bits>1</Bits>
<Attribute>address</Attribute>
<CType>int</CType>
</RtlPorts>
<RtlPorts>
<name>img_out_1_ce0</name>
<Object>img_out_1</Object>
<Type>array</Type>
<Scope></Scope>
<IOProtocol>ap_memory</IOProtocol>
<IOConfig></IOConfig>
<Dir>out</Dir>
<Bits>1</Bits>
<Attribute>control</Attribute>
<CType>int</CType>
</RtlPorts>
<RtlPorts>
<name>img_out_1_we0</name>
<Object>img_out_1</Object>
<Type>array</Type>
<Scope></Scope>
<IOProtocol>ap_memory</IOProtocol>
<IOConfig></IOConfig>
<Dir>out</Dir>
<Bits>1</Bits>
<Attribute>control</Attribute>
<CType>int</CType>
</RtlPorts>
<RtlPorts>
<name>img_out_1_d0</name>
<Object>img_out_1</Object>
<Type>array</Type>
<Scope></Scope>
<IOProtocol>ap_memory</IOProtocol>
<IOConfig></IOConfig>
<Dir>out</Dir>
<Bits>8</Bits>
<Attribute>data</Attribute>
<CType>int</CType>
</RtlPorts>
<RtlPorts>
<name>weights_0_address0</name>
<Object>weights_0</Object>
<Type>array</Type>
<Scope></Scope>
<IOProtocol>ap_memory</IOProtocol>
<IOConfig></IOConfig>
<Dir>out</Dir>
<Bits>3</Bits>
<Attribute>address</Attribute>
<CType>int</CType>
</RtlPorts>
<RtlPorts>
<name>weights_0_ce0</name>
<Object>weights_0</Object>
<Type>array</Type>
<Scope></Scope>
<IOProtocol>ap_memory</IOProtocol>
<IOConfig></IOConfig>
<Dir>out</Dir>
<Bits>1</Bits>
<Attribute>control</Attribute>
<CType>int</CType>
</RtlPorts>
<RtlPorts>
<name>weights_0_q0</name>
<Object>weights_0</Object>
<Type>array</Type>
<Scope></Scope>
<IOProtocol>ap_memory</IOProtocol>
<IOConfig></IOConfig>
<Dir>in</Dir>
<Bits>8</Bits>
<Attribute>data</Attribute>
<CType>int</CType>
</RtlPorts>
<RtlPorts>
<name>weights_1_address0</name>
<Object>weights_1</Object>
<Type>array</Type>
<Scope></Scope>
<IOProtocol>ap_memory</IOProtocol>
<IOConfig></IOConfig>
<Dir>out</Dir>
<Bits>3</Bits>
<Attribute>address</Attribute>
<CType>int</CType>
</RtlPorts>
<RtlPorts>
<name>weights_1_ce0</name>
<Object>weights_1</Object>
<Type>array</Type>
<Scope></Scope>
<IOProtocol>ap_memory</IOProtocol>
<IOConfig></IOConfig>
<Dir>out</Dir>
<Bits>1</Bits>
<Attribute>control</Attribute>
<CType>int</CType>
</RtlPorts>
<RtlPorts>
<name>weights_1_q0</name>
<Object>weights_1</Object>
<Type>array</Type>
<Scope></Scope>
<IOProtocol>ap_memory</IOProtocol>
<IOConfig></IOConfig>
<Dir>in</Dir>
<Bits>8</Bits>
<Attribute>data</Attribute>
<CType>int</CType>
</RtlPorts>
</InterfaceSummary>
</Module>
</ModuleInformation>

<FIFOInformation>
</FIFOInformation>

</profile>
